{
  "generated_at": "2026-07-12T05:20:23Z",
  "total_apps": 1148,
  "catalog_sha256": "b041e49aed844b10a23e7b5db96f3b0f47358ccd896e981a3026deab3ff2e102",
  "channels": {
    "stable": {
      "total_apps": 1,
      "warning": null
    },
    "beta": {
      "total_apps": 0,
      "warning": "Generally safe, but minor behavior may change."
    },
    "edge": {
      "total_apps": 0,
      "warning": "Experimental builds. APIs and behavior may change without notice."
    },
    "incubator": {
      "total_apps": 1147,
      "warning": "Candidate apps from external sources under evaluation."
    }
  },
  "sources": [
    {
      "id": "awesome-docker-compose",
      "repo": "https://awesome-docker-compose.com",
      "commit": "html-0aae19fc3f2c9fd4",
      "total_apps": 770,
      "generated_at": "2026-07-12T05:19:05Z"
    },
    {
      "id": "umbrel",
      "repo": "https://github.com/getumbrel/umbrel-apps.git",
      "commit": "9f636edda0ca721d8f5bce19d2a8cecc3dea7871",
      "total_apps": 379,
      "generated_at": "2026-07-12T05:12:53Z"
    }
  ]
}
